{
  "$schema": "https://developer.microsoft.com/json-schemas/fabric/item/report/definition/visualContainer/2.10.0/schema.json",
  "name": "cadc9a6b085477191c34",
  "position": {
    "x": 0,
    "y": 268.81325509147393,
    "z": 1,
    "height": 434.23679668622708,
    "width": 652.150500517777,
    "tabOrder": 1
  },
  "visual": {
    "visualType": "pivotTable",
    "query": {
      "queryState": {
        "Rows": {
          "projections": [
            {
              "field": {
                "Column": {
                  "Expression": {
                    "SourceRef": {
                      "Entity": "DimCostCenters"
                    }
                  },
                  "Property": "Division"
                }
              },
              "queryRef": "DimCostCenters.Division",
              "nativeQueryRef": "Division",
              "active": true
            }
          ]
        },
        "Values": {
          "projections": [
            {
              "field": {
                "Measure": {
                  "Expression": {
                    "SourceRef": {
                      "Entity": "_Measures"
                    }
                  },
                  "Property": "TotalBudget"
                }
              },
              "queryRef": "_Measures.TotalBudget",
              "nativeQueryRef": "TotalBudget"
            },
            {
              "field": {
                "Measure": {
                  "Expression": {
                    "SourceRef": {
                      "Entity": "_Measures"
                    }
                  },
                  "Property": "TotalActualSpend"
                }
              },
              "queryRef": "_Measures.TotalActualSpend",
              "nativeQueryRef": "TotalActualSpend"
            },
            {
              "field": {
                "Measure": {
                  "Expression": {
                    "SourceRef": {
                      "Entity": "_Measures"
                    }
                  },
                  "Property": "BudgetVariance"
                }
              },
              "queryRef": "_Measures.BudgetVariance",
              "nativeQueryRef": "BudgetVariance"
            }
          ]
        }
      },
      "sortDefinition": {
        "sort": [
          {
            "field": {
              "Measure": {
                "Expression": {
                  "SourceRef": {
                    "Entity": "_Measures"
                  }
                },
                "Property": "TotalBudget"
              }
            },
            "direction": "Descending"
          }
        ]
      }
    },
    "objects": {
      "values": [
        {
          "properties": {
            "backColorPrimary": {
              "solid": {
                "color": {
                  "expr": {
                    "ThemeDataColor": {
                      "ColorId": 3,
                      "Percent": 0
                    }
                  }
                }
              }
            },
            "fontColorPrimary": {
              "solid": {
                "color": {
                  "expr": {
                    "ThemeDataColor": {
                      "ColorId": 0,
                      "Percent": 0
                    }
                  }
                }
              }
            },
            "fontColorSecondary": {
              "solid": {
                "color": {
                  "expr": {
                    "ThemeDataColor": {
                      "ColorId": 0,
                      "Percent": 0
                    }
                  }
                }
              }
            },
            "backColorSecondary": {
              "solid": {
                "color": {
                  "expr": {
                    "ThemeDataColor": {
                      "ColorId": 3,
                      "Percent": 0
                    }
                  }
                }
              }
            },
            "bandedRowHeaders": {
              "expr": {
                "Literal": {
                  "Value": "false"
                }
              }
            },
            "fontSize": {
              "expr": {
                "Literal": {
                  "Value": "14D"
                }
              }
            }
          }
        },
        {
          "properties": {
            "fontColor": {
              "solid": {
                "color": {
                  "expr": {
                    "Conditional": {
                      "Cases": [
                        {
                          "Condition": {
                            "Comparison": {
                              "ComparisonKind": 2,
                              "Left": {
                                "Measure": {
                                  "Expression": {
                                    "SourceRef": {
                                      "Entity": "_Measures"
                                    }
                                  },
                                  "Property": "BudgetVariance"
                                }
                              },
                              "Right": {
                                "Literal": {
                                  "Value": "0D"
                                }
                              }
                            }
                          },
                          "Value": {
                            "Literal": {
                              "Value": "'#FFFFFF'"
                            }
                          }
                        },
                        {
                          "Condition": {
                            "Comparison": {
                              "ComparisonKind": 3,
                              "Left": {
                                "Measure": {
                                  "Expression": {
                                    "SourceRef": {
                                      "Entity": "_Measures"
                                    }
                                  },
                                  "Property": "BudgetVariance"
                                }
                              },
                              "Right": {
                                "Literal": {
                                  "Value": "0D"
                                }
                              }
                            }
                          },
                          "Value": {
                            "Literal": {
                              "Value": "'#FF6B6B'"
                            }
                          }
                        }
                      ]
                    }
                  }
                }
              }
            }
          },
          "selector": {
            "data": [
              {
                "dataViewWildcard": {
                  "matchingOption": 1
                }
              }
            ],
            "metadata": "_Measures.BudgetVariance"
          }
        }
      ],
      "columnHeaders": [
        {
          "properties": {
            "backColor": {
              "solid": {
                "color": {
                  "expr": {
                    "ThemeDataColor": {
                      "ColorId": 0,
                      "Percent": -0.5
                    }
                  }
                }
              }
            },
            "fontColor": {
              "solid": {
                "color": {
                  "expr": {
                    "ThemeDataColor": {
                      "ColorId": 0,
                      "Percent": 0
                    }
                  }
                }
              }
            },
            "bold": {
              "expr": {
                "Literal": {
                  "Value": "true"
                }
              }
            },
            "fontSize": {
              "expr": {
                "Literal": {
                  "Value": "14D"
                }
              }
            }
          }
        }
      ],
      "rowHeaders": [
        {
          "properties": {
            "fontColor": {
              "solid": {
                "color": {
                  "expr": {
                    "ThemeDataColor": {
                      "ColorId": 0,
                      "Percent": 0
                    }
                  }
                }
              }
            },
            "backColor": {
              "solid": {
                "color": {
                  "expr": {
                    "ThemeDataColor": {
                      "ColorId": 3,
                      "Percent": 0
                    }
                  }
                }
              }
            },
            "fontSize": {
              "expr": {
                "Literal": {
                  "Value": "14D"
                }
              }
            }
          }
        }
      ],
      "columnWidth": [
        {
          "properties": {
            "value": {
              "expr": {
                "Literal": {
                  "Value": "131.85232337663626D"
                }
              }
            }
          },
          "selector": {
            "metadata": "_Measures.TotalBudget"
          }
        },
        {
          "properties": {
            "value": {
              "expr": {
                "Literal": {
                  "Value": "173.37975587353895D"
                }
              }
            }
          },
          "selector": {
            "metadata": "_Measures.TotalActualSpend"
          }
        },
        {
          "properties": {
            "value": {
              "expr": {
                "Literal": {
                  "Value": "177.85473087358395D"
                }
              }
            }
          },
          "selector": {
            "metadata": "_Measures.BudgetVariance"
          }
        },
        {
          "properties": {
            "value": {
              "expr": {
                "Literal": {
                  "Value": "150.89775455510943D"
                }
              }
            }
          },
          "selector": {
            "metadata": "DimCostCenters.Division"
          }
        }
      ],
      "columnTotal": [
        {
          "properties": {
            "fontColor": {
              "solid": {
                "color": {
                  "expr": {
                    "ThemeDataColor": {
                      "ColorId": 0,
                      "Percent": 0
                    }
                  }
                }
              }
            }
          }
        }
      ],
      "rowTotal": [
        {
          "properties": {
            "fontColor": {
              "solid": {
                "color": {
                  "expr": {
                    "ThemeDataColor": {
                      "ColorId": 0,
                      "Percent": 0
                    }
                  }
                }
              }
            }
          }
        }
      ]
    },
    "visualContainerObjects": {
      "background": [
        {
          "properties": {
            "color": {
              "solid": {
                "color": {
                  "expr": {
                    "ThemeDataColor": {
                      "ColorId": 3,
                      "Percent": 0
                    }
                  }
                }
              }
            }
          }
        }
      ]
    },
    "drillFilterOtherVisuals": true
  },
  "filterConfig": {
    "filters": [
      {
        "name": "453edc0ec091d0da0247",
        "field": {
          "Column": {
            "Expression": {
              "SourceRef": {
                "Entity": "DimCostCenters"
              }
            },
            "Property": "Division"
          }
        },
        "type": "Categorical"
      },
      {
        "name": "93024d717a440516c40e",
        "field": {
          "Measure": {
            "Expression": {
              "SourceRef": {
                "Entity": "_Measures"
              }
            },
            "Property": "TotalBudget"
          }
        },
        "type": "Advanced"
      },
      {
        "name": "152592d9064038002be8",
        "field": {
          "Measure": {
            "Expression": {
              "SourceRef": {
                "Entity": "_Measures"
              }
            },
            "Property": "TotalActualSpend"
          }
        },
        "type": "Advanced"
      },
      {
        "name": "5d9dc974162d6eec0eac",
        "field": {
          "Measure": {
            "Expression": {
              "SourceRef": {
                "Entity": "_Measures"
              }
            },
            "Property": "BudgetVariance"
          }
        },
        "type": "Advanced"
      }
    ]
  }
}